MANIFEST.in
setup.py
man/__init__.py
man/man.py
man/manconfig.py
man/mangeneralconfig.py
man.egg-info/PKG-INFO
man.egg-info/SOURCES.txt
man.egg-info/dependency_links.txt
man.egg-info/requires.txt
man.egg-info/top_level.txt
man/assets/pypi-classifiers.txt
man/functions/__init__.py
man/functions/generate.py
man/libtemplate/.gitignore
man/libtemplate/.travis.yml
man/libtemplate/LICENSE
man/libtemplate/readme.md
man/libtemplate/test/__init__.py
man/libtemplate/test/test_missing.py
man/libtemplate/{libname}/__init__.py
man/libtemplate/{libname}/core.py
test/test_manconfig.py