Metadata-Version: 1.0
Name: man
Version: 1.5.0
Summary: Project manager for pypi libraries
Home-page: https://github.com/ddorn/man
Author: Diego Dorn
Author-email: diego.dorn@free.fr
License: MIT
Keywords: libraries developpement deployment versioning setuptools management distribution packaging PyPi
Platform: UNKNOWN
